pycotacao/__init__.py
pycotacao/api.py
pycotacao-1.1.dist-info/DESCRIPTION.rst
pycotacao-1.1.dist-info/METADATA
pycotacao-1.1.dist-info/RECORD
pycotacao-1.1.dist-info/WHEEL
pycotacao-1.1.dist-info/metadata.json
pycotacao-1.1.dist-info/top_level.txt
