Metadata-Version: 2.0
Name: pycotacao
Version: 1.1
Summary: Wrapper API for X-Rates from Banco Central.
Home-page: https://github.com/CaioWzy/PyCotacao
Author: CaioWzy
Author-email: mail@caiowzy.dev
Maintainer: CaioWzy
Maintainer-email: mail@caiowzy.dev
License: MIT
Project-URL: Code, https://github.com/CaioWzy/PyCotacao
Project-URL: Issue tracker, https://github.com/CaioWzy/PyCotacao/issues
Platform: UNKNOWN
Classifier: Development Status :: 5 - Production/Stable
Classifier: Intended Audience :: Developers
Classifier: License :: OSI Approved :: MIT License
Classifier: Operating System :: OS Independent
Classifier: Programming Language :: Python :: 3.6
Classifier: Programming Language :: Python :: 3.7
Classifier: Programming Language :: Python :: 3.8
Classifier: Programming Language :: Python :: Implementation :: CPython
Classifier: Programming Language :: Python :: Implementation :: PyPy
Classifier: Topic :: Software Development :: Libraries :: Python Modules
Requires-Python: >=3.6.*
Requires-Dist: python-dateutil (==2.8.1)
